health_watch/__init__.py
health_watch/agent.py
health_watch/system_checks/__init__.py
health_watch/system_checks/base.py
health_watch/system_checks/linux.py
health_watch/system_checks/macos.py
health_watch/system_checks/windows.py
health_watch-1.0.7.dist-info/METADATA
health_watch-1.0.7.dist-info/WHEEL
health_watch-1.0.7.dist-info/top_level.txt
health_watch-1.0.7.dist-info/RECORD
