Metadata-Version: 2.4
Name: health-watch
Version: 1.0.7
Summary: Cross-platform system monitoring utility
Author: Yashwant Jain
Classifier: Programming Language :: Python :: 3
Classifier: License :: OSI Approved :: MIT License
Classifier: Operating System :: OS Independent
Requires-Dist: requests
Requires-Dist: python-dotenv
Dynamic: author
Dynamic: classifier
Dynamic: requires-dist
Dynamic: summary
